terminal_bookmarks/__init__.py
terminal_bookmarks/cli/__init__.py
terminal_bookmarks/cli/commands.py
terminal_bookmarks/cli/help.py
terminal_bookmarks/cli/main.py
terminal_bookmarks/core/__init__.py
terminal_bookmarks/core/executor.py
terminal_bookmarks/core/manager.py
terminal_bookmarks/core/models.py
terminal_bookmarks/shell/integration.py
terminal_bookmarks/ui/formatting.py
terminal_bookmarks/utils/__init__.py
terminal_bookmarks/utils/config.py
terminal_bookmarks/utils/exceptions.py
terminal_bookmarks/utils/help.py
terminal_bookmarks/utils/id_generator.py
terminal_bookmarks/utils/platform.py
terminal_bookmarks/utils/styling.py
terminal_bookmarks-1.0.1.dist-info/LICENSE
terminal_bookmarks-1.0.1.dist-info/METADATA
terminal_bookmarks-1.0.1.dist-info/WHEEL
terminal_bookmarks-1.0.1.dist-info/entry_points.txt
terminal_bookmarks-1.0.1.dist-info/top_level.txt
terminal_bookmarks-1.0.1.dist-info/RECORD
