Metadata-Version: 2.2
Name: terminal-bookmarks
Version: 1.0.1
Summary: A command-line bookmark manager for your terminal commands
Author-email: Amogh Agrawal <amogh.ggn@gmail.com>
License: MIT
Project-URL: Homepage, https://github.com/amogh/terminal_bookmarks
Project-URL: Repository, https://github.com/amogh/terminal_bookmarks.git
Project-URL: Bug Tracker, https://github.com/amogh/terminal_bookmarks/issues
Keywords: terminal,bookmarks,cli,commands,productivity
Classifier: Development Status :: 5 - Production/Stable
Classifier: Environment :: Console
Classifier: Intended Audience :: Developers
Classifier: Intended Audience :: System Administrators
Classifier: License :: OSI Approved :: MIT License
Classifier: Operating System :: OS Independent
Classifier: Programming Language :: Python :: 3
Classifier: Programming Language :: Python :: 3.8
Classifier: Programming Language :: Python :: 3.9
Classifier: Programming Language :: Python :: 3.10
Classifier: Programming Language :: Python :: 3.11
Classifier: Topic :: System :: Shells
Classifier: Topic :: Utilities
Requires-Python: >=3.8
License-File: LICENSE
Requires-Dist: click>=8.0.0
Requires-Dist: rich>=10.0.0
Dynamic: requires-python
